mastercard_merchant_identifier_py3-1.0.5.2.dist-info/DESCRIPTION.rst
mastercard_merchant_identifier_py3-1.0.5.2.dist-info/METADATA
mastercard_merchant_identifier_py3-1.0.5.2.dist-info/RECORD
mastercard_merchant_identifier_py3-1.0.5.2.dist-info/WHEEL
mastercard_merchant_identifier_py3-1.0.5.2.dist-info/metadata.json
mastercard_merchant_identifier_py3-1.0.5.2.dist-info/top_level.txt
mastercardmerchantidentifier/__init__.py
mastercardmerchantidentifier/merchantidentifier.py
mastercardmerchantidentifier/resourceconfig.py
