Metadata-Version: 2.0
Name: mastercard-merchant-identifier-py3
Version: 1.0.5.2
Summary: MasterCard Merchant Identifier Python DK modified to work with Python 3
Home-page: https://github.com/candeias/mastercard_merchant_identifier
Author: Rogerio Candeias
Author-email: rogerio.candeias@gmail.com
License: BSD2
Platform: UNKNOWN
Classifier: Intended Audience :: Developers
Classifier: Natural Language :: English
Classifier: Operating System :: OS Independent
Classifier: Programming Language :: Python
Classifier: Programming Language :: Python :: 3.6
Classifier: Topic :: Software Development :: Libraries :: Python Modules
Requires-Dist: mastercard-api-core-py3 (<1.5.0,>=1.4.0)
